eventbrite/__init__.py
eventbrite/access_methods.py
eventbrite/apiv3_url_mapping.json
eventbrite/client.py
eventbrite/compat.py
eventbrite/decorators.py
eventbrite/exceptions.py
eventbrite/models.py
eventbrite/utils.py
eventbrite-3.3.3.dist-info/DESCRIPTION.rst
eventbrite-3.3.3.dist-info/METADATA
eventbrite-3.3.3.dist-info/metadata.json
eventbrite-3.3.3.dist-info/RECORD
eventbrite-3.3.3.dist-info/top_level.txt
eventbrite-3.3.3.dist-info/WHEEL
